MANIFEST.in
README.md
setup.py
pyquil/__init__.py
pyquil/device.py
pyquil/gates.py
pyquil/job_results.py
pyquil/kraus.py
pyquil/magic.py
pyquil/noise.py
pyquil/parameters.py
pyquil/parser.py
pyquil/paulis.py
pyquil/qpu.py
pyquil/quil.py
pyquil/quilatom.py
pyquil/quilbase.py
pyquil/wavefunction.py
pyquil/_parser/PyQuilListener.py
pyquil/_parser/__init__.py
pyquil/_parser/gen3/QuilLexer.py
pyquil/_parser/gen3/QuilListener.py
pyquil/_parser/gen3/QuilParser.py
pyquil/_parser/gen3/__init__.py
pyquil/api/__init__.py
pyquil/api/_base_connection.py
pyquil/api/_benchmark.py
pyquil/api/_compiler.py
pyquil/api/_config.py
pyquil/api/_devices.py
pyquil/api/_error_reporting.py
pyquil/api/_errors.py
pyquil/api/_job.py
pyquil/api/_qac.py
pyquil/api/_qam.py
pyquil/api/_qpu.py
pyquil/api/_quantum_computer.py
pyquil/api/_qvm.py
pyquil/api/_wavefunction_simulator.py
pyquil/latex/__init__.py
pyquil/latex/latex_config.py
pyquil/latex/latex_generation.py
qcs/__init__.py
qcs/gates.py
qcs/paulis.py
qcs.egg-info/PKG-INFO
qcs.egg-info/SOURCES.txt
qcs.egg-info/dependency_links.txt
qcs.egg-info/requires.txt
qcs.egg-info/top_level.txt