Metadata-Version: 2.1
Name: qcs
Version: 2.1.0
Summary: A Python library to generate Quantum Instruction Language (Quil) Programs.
Home-page: https://github.com/rigetti/pyquil.git
Author: Rigetti Computing
Author-email: softapps@rigetti.com
License: Apache-2.0
Keywords: quantum quil programming hybrid
Platform: UNKNOWN
Classifier: Development Status :: 5 - Production/Stable
Classifier: License :: OSI Approved :: Apache Software License
Classifier: Programming Language :: Python :: 3
Classifier: Operating System :: OS Independent
Requires-Python: >=3.5
